mcp_dagster/__init__.py
mcp_dagster/__main__.py
mcp_dagster/server.py
mcp_server_dagster-0.1.2.dist-info/METADATA
mcp_server_dagster-0.1.2.dist-info/WHEEL
mcp_server_dagster-0.1.2.dist-info/entry_points.txt
mcp_server_dagster-0.1.2.dist-info/licenses/LICENSE
mcp_server_dagster-0.1.2.dist-info/RECORD
