Metadata-Version: 2.4
Name: mcp-server-dagster
Version: 0.1.2
Summary: Add your description here
License-File: LICENSE
Requires-Python: >=3.12
Requires-Dist: dagster-webserver>=1.10.9
Requires-Dist: dagster>=1.10.9
Requires-Dist: mcp[cli]>=1.6.0
Requires-Dist: openai-agents>=0.0.9
Requires-Dist: pandas>=2.2.3
Requires-Dist: pytest-asyncio>=0.26.0
Requires-Dist: pytest>=8.3.5
Requires-Dist: ruff>=0.11.4
Requires-Dist: scikit-learn>=1.6.1
